gif2ascii/GifAscii.py
gif2ascii/__init__.py
gif2ascii/__main__.py
gif2ascii/clear.py
gif2ascii-0.1.4.dist-info/METADATA
gif2ascii-0.1.4.dist-info/WHEEL
gif2ascii-0.1.4.dist-info/top_level.txt
gif2ascii-0.1.4.dist-info/RECORD
