Metadata-Version: 2.1
Name: gif2ascii
Version: 0.1.4
Summary: Gif to ASCII
Author: Shobhit Bhosure
Author-email: <shobhitbhosure7@gmail.com>
Project-URL: Source, https://github.com/shobhit99/gif2ascii/
Keywords: python,ascii gif,terminal gif,ascii art,terminal art
Classifier: Intended Audience :: Developers
Classifier: Programming Language :: Python :: 3
Classifier: Operating System :: Unix
Classifier: Operating System :: MacOS :: MacOS X
Classifier: Operating System :: Microsoft :: Windows
Requires-Dist: Pillow
Requires-Dist: argparse
